{
  "version": "2.1",
  "units_supported": [
    "metric",
    "imperial"
  ],
  "conversion": {
    "mm_to_in": 0.0393700787,
    "in_to_mm": 25.4,
    "m_to_ft": 3.280839895,
    "ft_to_m": 0.3048,
    "kw_to_hp": 1.34102209,
    "hp_to_kw": 0.745699872
  },
  "ui_unit_labels": {
    "metric": {
      "diam": "mm",
      "fz": "mm",
      "ap": "mm",
      "stickout": "mm",
      "ae_percent": "%D",
      "vc": "m/min",
      "feed": "mm/min",
      "rpm": "rpm",
      "power": "kW",
      "torque": "N·m",
      "mrr": "cm³/min",
      "ra": "µm"
    },
    "imperial": {
      "diam": "in",
      "fz": "in",
      "ap": "in",
      "stickout": "in",
      "ae_percent": "%D",
      "vc": "SFM",
      "feed": "IPM",
      "rpm": "rpm",
      "power": "hp",
      "torque": "lbf·ft",
      "mrr": "in³/min",
      "ra": "µin"
    }
  },
  "defaults": {
    "rpm_limit": 12000,
    "feed_max_mm_min": 30000,
    "prudence": 0.9,
    "holder": "ER Collet",
    "stickout_mm": 25,
    "ae_percent": 25,
    "ap_mm": 5,
    "efficiency": 0.8,
    "vibe_gauss": {
      "mu": 0.75,
      "sigma": 0.2
    }
  },
  "vibration": {
    "avoid_band_hz": [
      600,
      900
    ],
    "rpm_shift_pct": 0.12,
    "risk_threshold": 0.85,
    "weights": {
      "ld": 0.55,
      "ae": 0.2,
      "ap": 0.15,
      "fz": 0.1
    }
  },
  "holders": [
    {
      "id": "ER Collet",
      "label": "Portapinzas ER genérico",
      "stiffness_factor": 1.0,
      "balance_G2_5_rpm": 12000
    },
    {
      "id": "Heavy ER",
      "label": "Portapinzas ER reforzado",
      "stiffness_factor": 1.1,
      "balance_G2_5_rpm": 15000
    },
    {
      "id": "REGOFIX_ER_HiQ",
      "label": "REGO-FIX ER (Hi-Q/Pro)",
      "stiffness_factor": 1.1,
      "balance_G2_5_rpm": 25000
    },
    {
      "id": "REGOFIX_powRgrip",
      "label": "REGO-FIX powRgrip (PG)",
      "stiffness_factor": 1.4,
      "balance_G2_5_rpm": 30000
    },
    {
      "id": "Hydraulic",
      "label": "Portaherramienta hidráulico",
      "stiffness_factor": 1.25,
      "balance_G2_5_rpm": 25000
    },
    {
      "id": "Shrinkfit",
      "label": "Termoencogible (shrinkfit)",
      "stiffness_factor": 1.35,
      "balance_G2_5_rpm": 30000
    },
    {
      "id": "MillingChuck",
      "label": "Milling/Power Chuck",
      "stiffness_factor": 1.2,
      "balance_G2_5_rpm": 18000
    },
    {
      "id": "Weldon",
      "label": "Mango tipo Weldon",
      "stiffness_factor": 1.15,
      "balance_G2_5_rpm": 12000
    }
  ],
  "machine_profiles": [
    {
      "id": "Haas_VF2",
      "brand": "Haas",
      "name": "VF-2",
      "type": "VMC",
      "axes": 3,
      "rpm_max": 7500,
      "power_kw": 22,
      "torque_nm": 100,
      "feed_max_mm_min": 10000,
      "units": "metric"
    },
    {
      "id": "Haas_VF2SS",
      "brand": "Haas",
      "name": "VF-2SS",
      "type": "VMC",
      "axes": 3,
      "rpm_max": 12000,
      "power_kw": 22,
      "torque_nm": 90,
      "feed_max_mm_min": 25000,
      "units": "metric"
    },
    {
      "id": "Haas_ST20Y",
      "brand": "Haas",
      "name": "ST-20Y",
      "type": "Lathe",
      "axes": 4,
      "rpm_max": 4000,
      "power_kw": 20,
      "torque_nm": 200,
      "feed_max_mm_min": 15000,
      "units": "metric"
    },
    {
      "id": "Haas_UMC500",
      "brand": "Haas",
      "name": "UMC-500",
      "type": "VMC-5X",
      "axes": 5,
      "rpm_max": 15000,
      "power_kw": 22,
      "torque_nm": 90,
      "feed_max_mm_min": 30000,
      "units": "metric"
    },
    {
      "id": "Brother_S500",
      "brand": "Brother",
      "name": "S500",
      "type": "VMC",
      "axes": 3,
      "rpm_max": 10000,
      "power_kw": 5.5,
      "torque_nm": 35,
      "feed_max_mm_min": 30000,
      "units": "metric"
    },
    {
      "id": "Brother_S700X1",
      "brand": "Brother",
      "name": "S700X1",
      "type": "VMC",
      "axes": 3,
      "rpm_max": 27000,
      "power_kw": 18.9,
      "torque_nm": 30,
      "feed_max_mm_min": 50000,
      "units": "metric"
    },
    {
      "id": "Fanuc_Robodrill_aD21",
      "brand": "Fanuc",
      "name": "Robodrill a-D21",
      "type": "VMC",
      "axes": 3,
      "rpm_max": 24000,
      "power_kw": 11,
      "torque_nm": 35,
      "feed_max_mm_min": 54000,
      "units": "metric"
    },
    {
      "id": "Okuma_M560V",
      "brand": "Okuma",
      "name": "Genos M560-V",
      "type": "VMC",
      "axes": 3,
      "rpm_max": 15000,
      "power_kw": 26,
      "torque_nm": 140,
      "feed_max_mm_min": 32000,
      "units": "metric"
    },
    {
      "id": "DMG_CMX1100V",
      "brand": "DMG MORI",
      "name": "CMX 1100 V",
      "type": "VMC",
      "axes": 3,
      "rpm_max": 12000,
      "power_kw": 12,
      "torque_nm": 70,
      "feed_max_mm_min": 30000,
      "units": "metric"
    },
    {
      "id": "Doosan_DNM5700",
      "brand": "DN Solutions",
      "name": "DNM 5700",
      "type": "VMC",
      "axes": 3,
      "rpm_max": 12000,
      "power_kw": 18.5,
      "torque_nm": 118,
      "feed_max_mm_min": 30000,
      "units": "metric"
    },
    {
      "id": "Mazak_VCN530C",
      "brand": "Mazak",
      "name": "VCN-530C",
      "type": "VMC",
      "axes": 3,
      "rpm_max": 12000,
      "power_kw": 18.5,
      "torque_nm": 119,
      "feed_max_mm_min": 30000,
      "units": "metric"
    },
    {
      "id": "Mikron_HSM400U",
      "brand": "GF Mikron",
      "name": "HSM 400U",
      "type": "VMC-5X",
      "axes": 5,
      "rpm_max": 42000,
      "power_kw": 13,
      "torque_nm": 30,
      "feed_max_mm_min": 60000,
      "units": "metric"
    },
    {
      "id": "Hurco_TM8i",
      "brand": "Hurco",
      "name": "TM8i",
      "type": "Lathe",
      "axes": 2,
      "rpm_max": 4800,
      "power_kw": 11,
      "torque_nm": 100,
      "feed_max_mm_min": 12000,
      "units": "metric"
    }
  ],
  "materials": []
}
